whisper_realtime_transcriber/__init__.py
whisper_realtime_transcriber/__main__.py
whisper_realtime_transcriber/api.py
whisper_realtime_transcriber/input_stream_generator.py
whisper_realtime_transcriber/realtime_transcriber.py
whisper_realtime_transcriber/whisper_model.py
whisper_realtime_transcriber/utils/__init__.py
whisper_realtime_transcriber/utils/utils.py
whisper_realtime_transcriber-1.1.0.dist-info/licenses/LICENSE
whisper_realtime_transcriber-1.1.0.dist-info/METADATA
whisper_realtime_transcriber-1.1.0.dist-info/WHEEL
whisper_realtime_transcriber-1.1.0.dist-info/top_level.txt
whisper_realtime_transcriber-1.1.0.dist-info/RECORD
