Metadata-Version: 2.4
Name: whisper-realtime-transcriber
Version: 1.1.0
Summary: Add your description here
Requires-Python: >=3.12
License-File: LICENSE
Requires-Dist: sounddevice>=0.5.0
Requires-Dist: ffmpeg-python>=0.2.0
Requires-Dist: asyncio>=3.4.3
Requires-Dist: accelerate>=0.33.0
Requires-Dist: torch>=2.4.0
Requires-Dist: transformers>=4.51.3
Requires-Dist: soundfile>=0.13.1
Requires-Dist: resampy>=0.4.3
Requires-Dist: fastapi>=0.115.12
Requires-Dist: uvicorn>=0.34.1
Dynamic: license-file
